app_pass/__init__.py
app_pass/__main__.py
app_pass/_app.py
app_pass/_commands.py
app_pass/_issues.py
app_pass/_jar.py
app_pass/_macho.py
app_pass/_notarize.py
app_pass/_util.py
app_pass-0.2.0.dist-info/licenses/LICENSE
app_pass-0.2.0.dist-info/METADATA
app_pass-0.2.0.dist-info/WHEEL
app_pass-0.2.0.dist-info/entry_points.txt
app_pass-0.2.0.dist-info/top_level.txt
app_pass-0.2.0.dist-info/RECORD
