Metadata-Version: 2.4
Name: app_pass
Version: 0.2.0
Summary: Tool to ensure an .app bundle pass the Gatekeeper on MacOS.
Author-email: Dominik Kutra <dominik.kutra@embl.de>
Maintainer-email: Dominik Kutra <dominik.kutra@embl.de>, ilastik team <team@ilastik.org>
License-Expression: MIT
Project-URL: Homepage, https://github.com/ilastik/app-pass
Project-URL: Issues, https://github.com/ilastik/app-pass/issues
Classifier: Programming Language :: Python :: 3
Classifier: Environment :: MacOS X
Requires-Python: >=3.10
License-File: LICENSE
Requires-Dist: lxml
Requires-Dist: packaging
Requires-Dist: rich
Provides-Extra: test
Requires-Dist: pytest; extra == "test"
Dynamic: license-file
